{
  "_note1": "KEEP THIS FILE! Check it into a version control system (VCS) like git.",
  "_note2": "ObjectBox manages crucial IDs for your object model. See docs for details.",
  "_note3": "If you have VCS merge conflicts, you must resolve them according to ObjectBox docs.",
  "entities": [
    {
      "id": "1:2522117341636349425",
      "lastPropertyId": "7:1571550371854984849",
      "name": "ObjectBoxUser",
      "properties": [
        {
          "id": "1:536244040443086042",
          "name": "id",
          "type": 6,
          "flags": 1
        },
        {
          "id": "2:8016144741500915640",
          "name": "fName",
          "type": 9
        },
        {
          "id": "3:1919579311574430672",
          "name": "lName",
          "type": 9
        },
        {
          "id": "4:5466757043895357396",
          "name": "birthMonth",
          "type": 6
        },
        {
          "id": "5:98543170472913625",
          "name": "birthDay",
          "type": 6
        },
        {
          "id": "6:11449171185759597",
          "name": "birthYear",
          "type": 6
        },
        {
          "id": "7:1571550371854984849",
          "name": "addedAt",
          "type": 9
        }
      ],
      "relations": []
    }
  ],
  "lastEntityId": "1:2522117341636349425",
  "lastIndexId": "0:0",
  "lastRelationId": "0:0",
  "lastSequenceId": "0:0",
  "modelVersion": 5,
  "modelVersionParserMinimum": 5,
  "retiredEntityUids": [],
  "retiredIndexUids": [],
  "retiredPropertyUids": [],
  "retiredRelationUids": [],
  "version": 1
}